{
    "get": "players/squads",
    "parameters": {
        "team": "653"
    },
    "errors": [],
    "results": 1,
    "paging": {
        "current": 1,
        "total": 1
    },
    "response": [
        {
            "team": {
                "id": 653,
                "name": "Cork City",
                "logo": "https://media.api-sports.io/football/teams/653.png"
            },
            "players": [
                {
                    "id": 284330,
                    "name": "A. Dowling",
                    "age": 21,
                    "number": null,
                    "position": "Goalkeeper",
                    "photo": "https://media.api-sports.io/football/players/284330.png"
                },
                {
                    "id": 417577,
                    "name": "D. Moynihan",
                    "age": null,
                    "number": null,
                    "position": "Goalkeeper",
                    "photo": "https://media.api-sports.io/football/players/417577.png"
                },
                {
                    "id": 20225,
                    "name": "B. Wade",
                    "age": 23,
                    "number": null,
                    "position": "Goalkeeper",
                    "photo": "https://media.api-sports.io/football/players/20225.png"
                },
                {
                    "id": 414180,
                    "name": "S. Bailey",
                    "age": null,
                    "number": null,
                    "position": "Defender",
                    "photo": "https://media.api-sports.io/football/players/414180.png"
                },
                {
                    "id": 69348,
                    "name": "C. Coleman",
                    "age": 26,
                    "number": null,
                    "position": "Defender",
                    "photo": "https://media.api-sports.io/football/players/69348.png"
                },
                {
                    "id": 69424,
                    "name": "D. Crowley",
                    "age": 23,
                    "number": null,
                    "position": "Defender",
                    "photo": "https://media.api-sports.io/football/players/69424.png"
                },
                {
                    "id": 201390,
                    "name": "C. Drinan",
                    "age": 23,
                    "number": null,
                    "position": "Defender",
                    "photo": "https://media.api-sports.io/football/players/201390.png"
                },
                {
                    "id": 457723,
                    "name": "M. Kiernan",
                    "age": null,
                    "number": null,
                    "position": "Defender",
                    "photo": "https://media.api-sports.io/football/players/457723.png"
                },
                {
                    "id": 69638,
                    "name": "C. Lyons",
                    "age": 23,
                    "number": null,
                    "position": "Defender",
                    "photo": "https://media.api-sports.io/football/players/69638.png"
                },
                {
                    "id": 390627,
                    "name": "Harry Nevin",
                    "age": 18,
                    "number": null,
                    "position": "Defender",
                    "photo": "https://media.api-sports.io/football/players/390627.png"
                },
                {
                    "id": 407939,
                    "name": "J. O&apos;Donovan",
                    "age": 19,
                    "number": null,
                    "position": "Defender",
                    "photo": "https://media.api-sports.io/football/players/407939.png"
                },
                {
                    "id": 69262,
                    "name": "G. Bolger",
                    "age": 35,
                    "number": null,
                    "position": "Midfielder",
                    "photo": "https://media.api-sports.io/football/players/69262.png"
                },
                {
                    "id": 163231,
                    "name": "N. Brookwell",
                    "age": 20,
                    "number": null,
                    "position": "Midfielder",
                    "photo": "https://media.api-sports.io/football/players/163231.png"
                },
                {
                    "id": 138408,
                    "name": "B. Coffey",
                    "age": 22,
                    "number": null,
                    "position": "Midfielder",
                    "photo": "https://media.api-sports.io/football/players/138408.png"
                },
                {
                    "id": 299873,
                    "name": "M. Dijksteel",
                    "age": 22,
                    "number": null,
                    "position": "Midfielder",
                    "photo": "https://media.api-sports.io/football/players/299873.png"
                },
                {
                    "id": 69741,
                    "name": "J. Doherty",
                    "age": 29,
                    "number": null,
                    "position": "Midfielder",
                    "photo": "https://media.api-sports.io/football/players/69741.png"
                },
                {
                    "id": 415393,
                    "name": "A. Healy",
                    "age": 18,
                    "number": null,
                    "position": "Midfielder",
                    "photo": "https://media.api-sports.io/football/players/415393.png"
                },
                {
                    "id": 418431,
                    "name": "C. Henderson",
                    "age": 19,
                    "number": null,
                    "position": "Midfielder",
                    "photo": "https://media.api-sports.io/football/players/418431.png"
                },
                {
                    "id": 319356,
                    "name": "E. McLaughlin",
                    "age": 21,
                    "number": null,
                    "position": "Midfielder",
                    "photo": "https://media.api-sports.io/football/players/319356.png"
                },
                {
                    "id": 410397,
                    "name": "M. Murray",
                    "age": 15,
                    "number": null,
                    "position": "Midfielder",
                    "photo": "https://media.api-sports.io/football/players/410397.png"
                },
                {
                    "id": 69245,
                    "name": "S. Murray",
                    "age": 30,
                    "number": null,
                    "position": "Midfielder",
                    "photo": "https://media.api-sports.io/football/players/69245.png"
                },
                {
                    "id": 437456,
                    "name": "Cathal O'Sullivan",
                    "age": null,
                    "number": null,
                    "position": "Midfielder",
                    "photo": "https://media.api-sports.io/football/players/437456.png"
                },
                {
                    "id": 69421,
                    "name": "C. Bargary",
                    "age": 23,
                    "number": null,
                    "position": "Attacker",
                    "photo": "https://media.api-sports.io/football/players/69421.png"
                },
                {
                    "id": 418429,
                    "name": "J. Fitzpatrick",
                    "age": null,
                    "number": null,
                    "position": "Attacker",
                    "photo": "https://media.api-sports.io/football/players/418429.png"
                },
                {
                    "id": 69432,
                    "name": "C. Murphy",
                    "age": 23,
                    "number": null,
                    "position": "Attacker",
                    "photo": "https://media.api-sports.io/football/players/69432.png"
                },
                {
                    "id": 457724,
                    "name": "H. Skieters",
                    "age": null,
                    "number": null,
                    "position": "Attacker",
                    "photo": "https://media.api-sports.io/football/players/457724.png"
                },
                {
                    "id": 444448,
                    "name": "J. Umeh",
                    "age": null,
                    "number": null,
                    "position": "Attacker",
                    "photo": "https://media.api-sports.io/football/players/444448.png"
                },
                {
                    "id": 135325,
                    "name": "N. Wood",
                    "age": 26,
                    "number": null,
                    "position": "Attacker",
                    "photo": "https://media.api-sports.io/football/players/135325.png"
                }
            ]
        }
    ]
}