{
    "get": "teams",
    "parameters": {
        "league": "2",
        "season": "2014"
    },
    "errors": [],
    "results": 77,
    "paging": {
        "current": 1,
        "total": 1
    },
    "response": [
        {
            "team": {
                "id": 40,
                "name": "Liverpool",
                "code": "LIV",
                "country": "England",
                "founded": 1892,
                "national": false,
                "logo": "https://media.api-sports.io/football/teams/40.png"
            },
            "venue": {
                "id": 550,
                "name": "Anfield",
                "address": "Anfield Road",
                "city": "Liverpool",
                "capacity": 55212,
                "surface": "grass",
                "image": "https://media.api-sports.io/football/venues/550.png"
            }
        },
        {
            "team": {
                "id": 42,
                "name": "Arsenal",
                "code": "ARS",
                "country": "England",
                "founded": 1886,
                "national": false,
                "logo": "https://media.api-sports.io/football/teams/42.png"
            },
            "venue": {
                "id": 494,
                "name": "Emirates Stadium",
                "address": "Queensland Road",
                "city": "London",
                "capacity": 60383,
                "surface": "grass",
                "image": "https://media.api-sports.io/football/venues/494.png"
            }
        },
        {
            "team": {
                "id": 49,
                "name": "Chelsea",
                "code": "CHE",
                "country": "England",
                "founded": 1905,
                "national": false,
                "logo": "https://media.api-sports.io/football/teams/49.png"
            },
            "venue": {
                "id": 519,
                "name": "Stamford Bridge",
                "address": "Fulham Road",
                "city": "London",
                "capacity": 41841,
                "surface": "grass",
                "image": "https://media.api-sports.io/football/venues/519.png"
            }
        },
        {
            "team": {
                "id": 50,
                "name": "Manchester City",
                "code": "MAC",
                "country": "England",
                "founded": 1880,
                "national": false,
                "logo": "https://media.api-sports.io/football/teams/50.png"
            },
            "venue": {
                "id": 555,
                "name": "Etihad Stadium",
                "address": "Rowsley Street",
                "city": "Manchester",
                "capacity": 55097,
                "surface": "grass",
                "image": "https://media.api-sports.io/football/venues/555.png"
            }
        },
        {
            "team": {
                "id": 79,
                "name": "Lille",
                "code": "LIL",
                "country": "France",
                "founded": 1944,
                "national": false,
                "logo": "https://media.api-sports.io/football/teams/79.png"
            },
            "venue": {
                "id": 19207,
                "name": "Decathlon Arena \u2013 Stade Pierre-Mauroy",
                "address": "261, Boulevard de Tournai, l&apos;H\u00f4tel de Ville",
                "city": "Villeneuve d&apos;Ascq",
                "capacity": 50083,
                "surface": "grass",
                "image": "https://media.api-sports.io/football/venues/19207.png"
            }
        },
        {
            "team": {
                "id": 85,
                "name": "Paris Saint Germain",
                "code": "PAR",
                "country": "France",
                "founded": 1970,
                "national": false,
                "logo": "https://media.api-sports.io/football/teams/85.png"
            },
            "venue": {
                "id": 671,
                "name": "Parc des Princes",
                "address": "24, rue du Commandant Guilbaud",
                "city": "Paris",
                "capacity": 47929,
                "surface": "grass",
                "image": "https://media.api-sports.io/football/venues/671.png"
            }
        },
        {
            "team": {
                "id": 91,
                "name": "Monaco",
                "code": "MON",
                "country": "France",
                "founded": 1919,
                "national": false,
                "logo": "https://media.api-sports.io/football/teams/91.png"
            },
            "venue": {
                "id": 20470,
                "name": "Stade Louis-II",
                "address": "7, avenue des Castelans",
                "city": "Monaco",
                "capacity": 18523,
                "surface": "grass",
                "image": "https://media.api-sports.io/football/venues/20470.png"
            }
        },
        {
            "team": {
                "id": 157,
                "name": "Bayern Munich",
                "code": "BAY",
                "country": "Germany",
                "founded": 1900,
                "national": false,
                "logo": "https://media.api-sports.io/football/teams/157.png"
            },
            "venue": {
                "id": 700,
                "name": "Allianz Arena",
                "address": "Werner-Heisenberg-Allee 25",
                "city": "M\u00fcnchen",
                "capacity": 75024,
                "surface": "grass",
                "image": "https://media.api-sports.io/football/venues/700.png"
            }
        },
        {
            "team": {
                "id": 165,
                "name": "Borussia Dortmund",
                "code": "DOR",
                "country": "Germany",
                "founded": 1909,
                "national": false,
                "logo": "https://media.api-sports.io/football/teams/165.png"
            },
            "venue": {
                "id": 19381,
                "name": "SIGNAL IDUNA PARK",
                "address": "Strobelalle 50",
                "city": "Dortmund",
                "capacity": 81365,
                "surface": "grass",
                "image": "https://media.api-sports.io/football/venues/19381.png"
            }
        },
        {
            "team": {
                "id": 168,
                "name": "Bayer Leverkusen",
                "code": "BAY",
                "country": "Germany",
                "founded": 1904,
                "national": false,
                "logo": "https://media.api-sports.io/football/teams/168.png"
            },
            "venue": {
                "id": 699,
                "name": "BayArena",
                "address": "Bismarckstr. 122-124",
                "city": "Leverkusen",
                "capacity": 30210,
                "surface": "grass",
                "image": "https://media.api-sports.io/football/venues/699.png"
            }
        },
        {
            "team": {
                "id": 174,
                "name": "FC Schalke 04",
                "code": "SCH",
                "country": "Germany",
                "founded": 1904,
                "national": false,
                "logo": "https://media.api-sports.io/football/teams/174.png"
            },
            "venue": {
                "id": 741,
                "name": "VELTINS-Arena",
                "address": "Arenaring 1",
                "city": "Gelsenkirchen",
                "capacity": 62271,
                "surface": "grass",
                "image": "https://media.api-sports.io/football/venues/741.png"
            }
        },
        {
            "team": {
                "id": 194,
                "name": "Ajax",
                "code": "AJA",
                "country": "Netherlands",
                "founded": 1900,
                "national": false,
                "logo": "https://media.api-sports.io/football/teams/194.png"
            },
            "venue": {
                "id": 1117,
                "name": "Johan Cruijff Arena",
                "address": "ArenA Boulevard 1",
                "city": "Amsterdam",
                "capacity": 54990,
                "surface": "grass",
                "image": "https://media.api-sports.io/football/venues/1117.png"
            }
        },
        {
            "team": {
                "id": 209,
                "name": "Feyenoord",
                "code": "FEY",
                "country": "Netherlands",
                "founded": 1908,
                "national": false,
                "logo": "https://media.api-sports.io/football/teams/209.png"
            },
            "venue": {
                "id": 1128,
                "name": "Stadion Feijenoord",
                "address": "Van Zandvlietplein 1",
                "city": "Rotterdam",
                "capacity": 51117,
                "surface": "grass",
                "image": "https://media.api-sports.io/football/venues/1128.png"
            }
        },
        {
            "team": {
                "id": 211,
                "name": "Benfica",
                "code": "BEN",
                "country": "Portugal",
                "founded": 1904,
                "national": false,
                "logo": "https://media.api-sports.io/football/teams/211.png"
            },
            "venue": {
                "id": 1265,
                "name": "Est\u00e1dio do Sport Lisboa e Benfica (da Luz)",
                "address": "Rua Jos\u00e9 Maria Nicolau",
                "city": "Lisboa",
                "capacity": 65647,
                "surface": "grass",
                "image": "https://media.api-sports.io/football/venues/1265.png"
            }
        },
        {
            "team": {
                "id": 212,
                "name": "FC Porto",
                "code": "POR",
                "country": "Portugal",
                "founded": 1893,
                "national": false,
                "logo": "https://media.api-sports.io/football/teams/212.png"
            },
            "venue": {
                "id": 1286,
                "name": "Est\u00e1dio Do Drag\u00e3o",
                "address": "Via Futebol Clube do Porto",
                "city": "Porto",
                "capacity": 50399,
                "surface": "grass",
                "image": "https://media.api-sports.io/football/venues/1286.png"
            }
        },
        {
            "team": {
                "id": 228,
                "name": "Sporting CP",
                "code": "SPO",
                "country": "Portugal",
                "founded": 1906,
                "national": false,
                "logo": "https://media.api-sports.io/football/teams/228.png"
            },
            "venue": {
                "id": 1293,
                "name": "Est\u00e1dio Jos\u00e9 Alvalade",
                "address": "Rua Professor Fernando da Fonseca",
                "city": "Lisboa",
                "capacity": 50466,
                "surface": "grass",
                "image": "https://media.api-sports.io/football/venues/1293.png"
            }
        },
        {
            "team": {
                "id": 247,
                "name": "Celtic",
                "code": "CEL",
                "country": "Scotland",
                "founded": 1888,
                "national": false,
                "logo": "https://media.api-sports.io/football/teams/247.png"
            },
            "venue": {
                "id": 1386,
                "name": "Celtic Park",
                "address": "18 Kerrydale Street",
                "city": "Glasgow",
                "capacity": 60832,
                "surface": "grass",
                "image": "https://media.api-sports.io/football/venues/1386.png"
            }
        },
        {
            "team": {
                "id": 271,
                "name": "KR Reykjavik",
                "code": "REY",
                "country": "Iceland",
                "founded": 1899,
                "national": false,
                "logo": "https://media.api-sports.io/football/teams/271.png"
            },
            "venue": {
                "id": 10591,
                "name": "KR-v\u00f6llur",
                "address": "Frostaskj\u00f3li 2",
                "city": "Reykjav\u00edk",
                "capacity": 2801,
                "surface": "grass",
                "image": "https://media.api-sports.io/football/venues/10591.png"
            }
        },
        {
            "team": {
                "id": 324,
                "name": "Stromsgodset",
                "code": "STR",
                "country": "Norway",
                "founded": 1907,
                "national": false,
                "logo": "https://media.api-sports.io/football/teams/324.png"
            },
            "venue": {
                "id": 1199,
                "name": "Marienlyst Stadion",
                "address": "Schwartzgata 2",
                "city": "Drammen",
                "capacity": 8935,
                "surface": "artificial turf",
                "image": "https://media.api-sports.io/football/venues/1199.png"
            }
        },
        {
            "team": {
                "id": 339,
                "name": "Legia Warszawa",
                "code": "LEG",
                "country": "Poland",
                "founded": 1916,
                "national": false,
                "logo": "https://media.api-sports.io/football/teams/339.png"
            },
            "venue": {
                "id": 1253,
                "name": "Stadion Miejski Legii Warszawa im. Marsza\u0142ka J\u00f3zefa Pi\u0142sudskiego",
                "address": "ul. \u0141azienkowska 3",
                "city": "Warszawa",
                "capacity": 31103,
                "surface": "grass",
                "image": "https://media.api-sports.io/football/venues/1253.png"
            }
        },
        {
            "team": {
                "id": 354,
                "name": "The New Saints",
                "code": "TNS",
                "country": "Wales",
                "founded": 1959,
                "national": false,
                "logo": "https://media.api-sports.io/football/teams/354.png"
            },
            "venue": {
                "id": 1684,
                "name": "Park Hall Stadium",
                "address": "Burma Road",
                "city": "Oswestry / Croesoswallt, Shropshire",
                "capacity": 2000,
                "surface": "artificial turf",
                "image": "https://media.api-sports.io/football/venues/1684.png"
            }
        },
        {
            "team": {
                "id": 375,
                "name": "Malmo FF",
                "code": "MAL",
                "country": "Sweden",
                "founded": 1910,
                "national": false,
                "logo": "https://media.api-sports.io/football/teams/375.png"
            },
            "venue": {
                "id": 1518,
                "name": "Eleda Stadion",
                "address": "Eric Persson v\u00e4g 1",
                "city": "Malm\u00f6",
                "capacity": 24148,
                "surface": "grass",
                "image": "https://media.api-sports.io/football/venues/1518.png"
            }
        },
        {
            "team": {
                "id": 388,
                "name": "Bate Borisov",
                "code": "BAT",
                "country": "Belarus",
                "founded": 1973,
                "national": false,
                "logo": "https://media.api-sports.io/football/teams/388.png"
            },
            "venue": {
                "id": 7764,
                "name": "Borisov Arena",
                "address": null,
                "city": "Borisov",
                "capacity": 13141,
                "surface": "grass",
                "image": "https://media.api-sports.io/football/venues/7764.png"
            }
        },
        {
            "team": {
                "id": 400,
                "name": "FC Copenhagen",
                "code": "COP",
                "country": "Denmark",
                "founded": 1992,
                "national": false,
                "logo": "https://media.api-sports.io/football/teams/400.png"
            },
            "venue": {
                "id": 11600,
                "name": "Parken",
                "address": "\u00d8ster All\u00e9 50",
                "city": "K\u00f8benhavn",
                "capacity": 38065,
                "surface": "grass",
                "image": "https://media.api-sports.io/football/venues/11600.png"
            }
        },
        {
            "team": {
                "id": 402,
                "name": "Aalborg",
                "code": "AAL",
                "country": "Denmark",
                "founded": 1885,
                "national": false,
                "logo": "https://media.api-sports.io/football/teams/402.png"
            },
            "venue": {
                "id": 440,
                "name": "Aalborg Portland Park",
                "address": "Harald Jensens Vej 9",
                "city": "Aalborg",
                "capacity": 13797,
                "surface": "grass",
                "image": "https://media.api-sports.io/football/venues/440.png"
            }
        },
        {
            "team": {
                "id": 492,
                "name": "Napoli",
                "code": "NAP",
                "country": "Italy",
                "founded": 1904,
                "national": false,
                "logo": "https://media.api-sports.io/football/teams/492.png"
            },
            "venue": {
                "id": 11904,
                "name": "Stadio Diego Armando Maradona",
                "address": "Pizzale Vincenzo Tecchio",
                "city": "Napoli",
                "capacity": 60240,
                "surface": "grass",
                "image": "https://media.api-sports.io/football/venues/11904.png"
            }
        },
        {
            "team": {
                "id": 496,
                "name": "Juventus",
                "code": "JUV",
                "country": "Italy",
                "founded": 1897,
                "national": false,
                "logo": "https://media.api-sports.io/football/teams/496.png"
            },
            "venue": {
                "id": 909,
                "name": "Allianz Stadium",
                "address": "Strada Comunale di Altessano 131",
                "city": "Torino",
                "capacity": 45666,
                "surface": "grass",
                "image": "https://media.api-sports.io/football/venues/909.png"
            }
        },
        {
            "team": {
                "id": 497,
                "name": "AS Roma",
                "code": "ROM",
                "country": "Italy",
                "founded": 1927,
                "national": false,
                "logo": "https://media.api-sports.io/football/teams/497.png"
            },
            "venue": {
                "id": 910,
                "name": "Stadio Olimpico",
                "address": "Viale dei Gladiatori, 2 / Via del Foro Italico",
                "city": "Roma",
                "capacity": 68530,
                "surface": "grass",
                "image": "https://media.api-sports.io/football/venues/910.png"
            }
        },
        {
            "team": {
                "id": 529,
                "name": "Barcelona",
                "code": "BAR",
                "country": "Spain",
                "founded": 1899,
                "national": false,
                "logo": "https://media.api-sports.io/football/teams/529.png"
            },
            "venue": {
                "id": 19939,
                "name": "Estadi Ol\u00edmpic Llu\u00eds Companys",
                "address": "Carrer de l&apos;Estadi",
                "city": "Barcelona",
                "capacity": 55926,
                "surface": "grass",
                "image": "https://media.api-sports.io/football/venues/19939.png"
            }
        },
        {
            "team": {
                "id": 530,
                "name": "Atletico Madrid",
                "code": "MAD",
                "country": "Spain",
                "founded": 1903,
                "national": false,
                "logo": "https://media.api-sports.io/football/teams/530.png"
            },
            "venue": {
                "id": 19217,
                "name": "Est\u00e1dio C\u00edvitas Metropolitano",
                "address": "Rosas",
                "city": "Madrid",
                "capacity": 70460,
                "surface": "grass",
                "image": "https://media.api-sports.io/football/venues/19217.png"
            }
        },
        {
            "team": {
                "id": 531,
                "name": "Athletic Club",
                "code": "BIL",
                "country": "Spain",
                "founded": 1898,
                "national": false,
                "logo": "https://media.api-sports.io/football/teams/531.png"
            },
            "venue": {
                "id": 1460,
                "name": "San Mam\u00e9s Barria",
                "address": "Rafael Moreno Pitxitxi Kalea",
                "city": "Bilbao",
                "capacity": 53289,
                "surface": "grass",
                "image": "https://media.api-sports.io/football/venues/1460.png"
            }
        },
        {
            "team": {
                "id": 541,
                "name": "Real Madrid",
                "code": "REA",
                "country": "Spain",
                "founded": 1902,
                "national": false,
                "logo": "https://media.api-sports.io/football/teams/541.png"
            },
            "venue": {
                "id": 1456,
                "name": "Estadio Santiago Bernab\u00e9u",
                "address": "Avenida de Concha Espina 1, Chamart\u00edn",
                "city": "Madrid",
                "capacity": 85454,
                "surface": "grass",
                "image": "https://media.api-sports.io/football/venues/1456.png"
            }
        },
        {
            "team": {
                "id": 549,
                "name": "Besiktas",
                "code": "BES",
                "country": "Turkey",
                "founded": 1903,
                "national": false,
                "logo": "https://media.api-sports.io/football/teams/549.png"
            },
            "venue": {
                "id": 20423,
                "name": "T\u00fcpra\u015f Stadyumu",
                "address": "Dolmabah\u00e7e Gazhane Caddesi, Be\u015fikta\u015f",
                "city": "\u0130stanbul",
                "capacity": 43500,
                "surface": "grass",
                "image": "https://media.api-sports.io/football/venues/20423.png"
            }
        },
        {
            "team": {
                "id": 550,
                "name": "Shakhtar Donetsk",
                "code": "SHA",
                "country": "Ukraine",
                "founded": 1936,
                "national": false,
                "logo": "https://media.api-sports.io/football/teams/550.png"
            },
            "venue": {
                "id": 20114,
                "name": "NSK Olimpiiskyi",
                "address": "vul. Velyka Vasylkivska 55",
                "city": "Kiev",
                "capacity": 70050,
                "surface": "grass",
                "image": "https://media.api-sports.io/football/venues/20114.png"
            }
        },
        {
            "team": {
                "id": 551,
                "name": "FC Basel 1893",
                "code": "BAS",
                "country": "Switzerland",
                "founded": 1893,
                "national": false,
                "logo": "https://media.api-sports.io/football/teams/551.png"
            },
            "venue": {
                "id": 1530,
                "name": "St. Jakob-Park",
                "address": "Sankt Jakob-Strasse 395",
                "city": "Basel",
                "capacity": 38512,
                "surface": "grass",
                "image": "https://media.api-sports.io/football/venues/1530.png"
            }
        },
        {
            "team": {
                "id": 552,
                "name": "Maribor",
                "code": "MAR",
                "country": "Slovenia",
                "founded": 1960,
                "national": false,
                "logo": "https://media.api-sports.io/football/teams/552.png"
            },
            "venue": {
                "id": 1441,
                "name": "Ljudski vrt",
                "address": "Mladinska ul. 29",
                "city": "Maribor",
                "capacity": 12994,
                "surface": "grass",
                "image": "https://media.api-sports.io/football/venues/1441.png"
            }
        },
        {
            "team": {
                "id": 553,
                "name": "Olympiakos Piraeus",
                "code": "OLY",
                "country": "Greece",
                "founded": 1925,
                "national": false,
                "logo": "https://media.api-sports.io/football/teams/553.png"
            },
            "venue": {
                "id": 775,
                "name": "Stadio Georgios Karaisk\u00e1ki",
                "address": "Poseidonos Avenue, Faliro",
                "city": "Piraeus",
                "capacity": 33296,
                "surface": "grass",
                "image": "https://media.api-sports.io/football/venues/775.png"
            }
        },
        {
            "team": {
                "id": 554,
                "name": "Anderlecht",
                "code": "AND",
                "country": "Belgium",
                "founded": 1908,
                "national": false,
                "logo": "https://media.api-sports.io/football/teams/554.png"
            },
            "venue": {
                "id": 174,
                "name": "Lotto Park",
                "address": "Avenue Th\u00e9o Verbeeck 2",
                "city": "Brussel",
                "capacity": 28063,
                "surface": "grass",
                "image": "https://media.api-sports.io/football/venues/174.png"
            }
        },
        {
            "team": {
                "id": 555,
                "name": "CSKA Moscow",
                "code": "CSK",
                "country": "Russia",
                "founded": 1911,
                "national": false,
                "logo": "https://media.api-sports.io/football/teams/555.png"
            },
            "venue": {
                "id": 1333,
                "name": "VEB Arena",
                "address": "3-ya Peschanaya ul.",
                "city": "Moskva",
                "capacity": 30000,
                "surface": "grass",
                "image": "https://media.api-sports.io/football/venues/1333.png"
            }
        },
        {
            "team": {
                "id": 556,
                "name": "Qarabag",
                "code": "KAR",
                "country": "Azerbaidjan",
                "founded": 1950,
                "national": false,
                "logo": "https://media.api-sports.io/football/teams/556.png"
            },
            "venue": {
                "id": 5799,
                "name": "Tofiq B\u0259hramov ad\u0131na Respublika stadionu",
                "address": "10 Fatali Khan Khoyski",
                "city": "Baku",
                "capacity": 31850,
                "surface": "grass",
                "image": "https://media.api-sports.io/football/venues/5799.png"
            }
        },
        {
            "team": {
                "id": 559,
                "name": "FCSB",
                "code": "STE",
                "country": "Romania",
                "founded": 1947,
                "national": false,
                "logo": "https://media.api-sports.io/football/teams/559.png"
            },
            "venue": {
                "id": 1326,
                "name": "Arena Na\u0163ional\u0103",
                "address": "Bulevardul Basarabia 37-39",
                "city": "Bucure\u015fti",
                "capacity": 55611,
                "surface": "grass",
                "image": "https://media.api-sports.io/football/venues/1326.png"
            }
        },
        {
            "team": {
                "id": 566,
                "name": "Ludogorets",
                "code": "LUD",
                "country": "Bulgaria",
                "founded": 1945,
                "national": false,
                "logo": "https://media.api-sports.io/football/teams/566.png"
            },
            "venue": {
                "id": 10547,
                "name": "Huvepharma Arena",
                "address": "bul. Severen",
                "city": "Razgrad",
                "capacity": 10422,
                "surface": "grass",
                "image": "https://media.api-sports.io/football/venues/10547.png"
            }
        },
        {
            "team": {
                "id": 568,
                "name": "Sheriff Tiraspol",
                "code": "SHE",
                "country": "Moldova",
                "founded": 1997,
                "national": false,
                "logo": "https://media.api-sports.io/football/teams/568.png"
            },
            "venue": {
                "id": 1093,
                "name": "Bolshaya Sportivnaya Arena",
                "address": "ul. K. Libnekhta 1/2",
                "city": "Tiraspol",
                "capacity": 13460,
                "surface": "grass",
                "image": "https://media.api-sports.io/football/venues/1093.png"
            }
        },
        {
            "team": {
                "id": 571,
                "name": "Red Bull Salzburg",
                "code": "SAL",
                "country": "Austria",
                "founded": 1933,
                "national": false,
                "logo": "https://media.api-sports.io/football/teams/571.png"
            },
            "venue": {
                "id": 148,
                "name": "Red Bull Arena",
                "address": "Stadionstrasse 2/3",
                "city": "Wals-Siezenheim",
                "capacity": 31895,
                "surface": "grass",
                "image": "https://media.api-sports.io/football/venues/148.png"
            }
        },
        {
            "team": {
                "id": 573,
                "name": "FK Partizan",
                "code": "PAR",
                "country": "Serbia",
                "founded": 1945,
                "national": false,
                "logo": "https://media.api-sports.io/football/teams/573.png"
            },
            "venue": {
                "id": 1424,
                "name": "Stadion Partizana",
                "address": "Humska 1",
                "city": "Beograd",
                "capacity": 32710,
                "surface": "grass",
                "image": "https://media.api-sports.io/football/venues/1424.png"
            }
        },
        {
            "team": {
                "id": 578,
                "name": "F91 Dudelange",
                "code": null,
                "country": "Luxembourg",
                "founded": 1991,
                "national": false,
                "logo": "https://media.api-sports.io/football/teams/578.png"
            },
            "venue": {
                "id": 1033,
                "name": "Stade Jos Nosbaum",
                "address": "Rue de Stade Jos Nosbaum",
                "city": "Dudelange",
                "capacity": 2558,
                "surface": "grass",
                "image": "https://media.api-sports.io/football/venues/1033.png"
            }
        },
        {
            "team": {
                "id": 586,
                "name": "FK Zalgiris Vilnius",
                "code": "ZAL",
                "country": "Lithuania",
                "founded": 1947,
                "national": false,
                "logo": "https://media.api-sports.io/football/teams/586.png"
            },
            "venue": {
                "id": 2612,
                "name": "S. Dariaus ir S. Gir\u0117no stadionas",
                "address": "\u0104\u017euolyno gatv\u0117",
                "city": "Kaunas",
                "capacity": 15315,
                "surface": "grass",
                "image": "https://media.api-sports.io/football/venues/2612.png"
            }
        },
        {
            "team": {
                "id": 588,
                "name": "Zrinjski",
                "code": "ZRI",
                "country": "Bosnia",
                "founded": 1905,
                "national": false,
                "logo": "https://media.api-sports.io/football/teams/588.png"
            },
            "venue": {
                "id": 202,
                "name": "Stadion Bijeli Brijeg",
                "address": "Stjepana Radica 45",
                "city": "Mostar",
                "capacity": 20000,
                "surface": "grass",
                "image": "https://media.api-sports.io/football/venues/202.png"
            }
        },
        {
            "team": {
                "id": 591,
                "name": "FC Santa Coloma",
                "code": "SAN",
                "country": "Andorra",
                "founded": 1986,
                "national": false,
                "logo": "https://media.api-sports.io/football/teams/591.png"
            },
            "venue": {
                "id": 30,
                "name": "Centre d'Entrenament de la FAF 1",
                "address": "Avenue de Santa Coloma",
                "city": "Santa Coloma",
                "capacity": 2000,
                "surface": "artificial turf",
                "image": "https://media.api-sports.io/football/venues/30.png"
            }
        },
        {
            "team": {
                "id": 596,
                "name": "Zenit",
                "code": "ZEN",
                "country": "Russia",
                "founded": 1925,
                "national": false,
                "logo": "https://media.api-sports.io/football/teams/596.png"
            },
            "venue": {
                "id": 1356,
                "name": "Saint-Petersburg Stadium",
                "address": "Futbolnaya al.",
                "city": "St. Petersburg",
                "capacity": 68134,
                "surface": "grass",
                "image": "https://media.api-sports.io/football/venues/1356.png"
            }
        },
        {
            "team": {
                "id": 604,
                "name": "Maccabi Tel Aviv",
                "code": "MAC",
                "country": "Israel",
                "founded": 1906,
                "national": false,
                "logo": "https://media.api-sports.io/football/teams/604.png"
            },
            "venue": {
                "id": 10592,
                "name": "Bloomfield Stadium",
                "address": "Ha-Tkuma Street",
                "city": "Tel-Aviv",
                "capacity": 29400,
                "surface": "grass",
                "image": "https://media.api-sports.io/football/venues/10592.png"
            }
        },
        {
            "team": {
                "id": 605,
                "name": "Skenderbeu Korce",
                "code": "SKE",
                "country": "Albania",
                "founded": 1909,
                "national": false,
                "logo": "https://media.api-sports.io/football/teams/605.png"
            },
            "venue": {
                "id": 2155,
                "name": "Stadiumi Sk\u00ebnderbeu",
                "address": "Rruga Gjiergi Kastrioti",
                "city": "Kor\u00e7\u00eb",
                "capacity": 11000,
                "surface": "grass",
                "image": "https://media.api-sports.io/football/venues/2155.png"
            }
        },
        {
            "team": {
                "id": 617,
                "name": "Panathinaikos",
                "code": "PAN",
                "country": "Greece",
                "founded": 1908,
                "national": false,
                "logo": "https://media.api-sports.io/football/teams/617.png"
            },
            "venue": {
                "id": 19929,
                "name": "Stadio Ap\u00f3stolos Nikolaidis",
                "address": "Leoforos Alexandras, Ampelokipi",
                "city": "Athens",
                "capacity": 16620,
                "surface": "grass",
                "image": "https://media.api-sports.io/football/venues/19929.png"
            }
        },
        {
            "team": {
                "id": 620,
                "name": "Dinamo Zagreb",
                "code": "ZAG",
                "country": "Croatia",
                "founded": 1911,
                "national": false,
                "logo": "https://media.api-sports.io/football/teams/620.png"
            },
            "venue": {
                "id": 412,
                "name": "Stadion Maksimir",
                "address": "Maksimirska cesta 128",
                "city": "Zagreb",
                "capacity": 37168,
                "surface": "grass",
                "image": "https://media.api-sports.io/football/venues/412.png"
            }
        },
        {
            "team": {
                "id": 628,
                "name": "Sparta Praha",
                "code": "SPA",
                "country": "Czech-Republic",
                "founded": 1893,
                "national": false,
                "logo": "https://media.api-sports.io/football/teams/628.png"
            },
            "venue": {
                "id": 19513,
                "name": "epet ARENA",
                "address": "Milady Hor\u00e1kov\u00e9 1066/98, Letn\u00e1",
                "city": "Praha",
                "capacity": 20854,
                "surface": "grass",
                "image": "https://media.api-sports.io/football/venues/19513.png"
            }
        },
        {
            "team": {
                "id": 645,
                "name": "Galatasaray",
                "code": "GAL",
                "country": "Turkey",
                "founded": 1905,
                "national": false,
                "logo": "https://media.api-sports.io/football/teams/645.png"
            },
            "venue": {
                "id": 19941,
                "name": "Rams Global Stadium",
                "address": "\u0130stanbul \u00c7evre Yolu, Aslantepe",
                "city": "\u0130stanbul",
                "capacity": 52695,
                "surface": "grass",
                "image": "https://media.api-sports.io/football/venues/19941.png"
            }
        },
        {
            "team": {
                "id": 649,
                "name": "HJK helsinki",
                "code": "HJK",
                "country": "Finland",
                "founded": 1907,
                "national": false,
                "logo": "https://media.api-sports.io/football/teams/649.png"
            },
            "venue": {
                "id": 615,
                "name": "Bolt Arena",
                "address": "Urheilukatu 1",
                "city": "Helsinki",
                "capacity": 10770,
                "surface": "artificial turf",
                "image": "https://media.api-sports.io/football/venues/615.png"
            }
        },
        {
            "team": {
                "id": 656,
                "name": "Slovan Bratislava",
                "code": "SLO",
                "country": "Slovakia",
                "founded": 1919,
                "national": false,
                "logo": "https://media.api-sports.io/football/teams/656.png"
            },
            "venue": {
                "id": 11914,
                "name": "\u0160tadi\u00f3n Teheln\u00e9 pole",
                "address": "Viktora Tegelhoffa 3, Nov\u00e9 Mesto",
                "city": "Bratislava",
                "capacity": 22500,
                "surface": "grass",
                "image": "https://media.api-sports.io/football/venues/11914.png"
            }
        },
        {
            "team": {
                "id": 659,
                "name": "Valletta FC",
                "code": "VAL",
                "country": "Malta",
                "founded": 1944,
                "national": false,
                "logo": "https://media.api-sports.io/football/teams/659.png"
            },
            "venue": {
                "id": 1067,
                "name": "MFA Centenary Stadium",
                "address": "Villagg Tas-Snajja&apos;",
                "city": "Ta&apos;Qali",
                "capacity": 2000,
                "surface": "artificial turf",
                "image": "https://media.api-sports.io/football/venues/1067.png"
            }
        },
        {
            "team": {
                "id": 663,
                "name": "FK Rabotnicki",
                "code": "RAB",
                "country": "Macedonia",
                "founded": 1937,
                "national": false,
                "logo": "https://media.api-sports.io/football/teams/663.png"
            },
            "venue": {
                "id": 1045,
                "name": "To\u0161e Proeski Arena",
                "address": "Gradski Park bb",
                "city": "Skopje",
                "capacity": 32580,
                "surface": "grass",
                "image": "https://media.api-sports.io/football/venues/1045.png"
            }
        },
        {
            "team": {
                "id": 667,
                "name": "Lincoln Red Imps FC",
                "code": "LIN",
                "country": "Gibraltar",
                "founded": null,
                "national": false,
                "logo": "https://media.api-sports.io/football/teams/667.png"
            },
            "venue": {
                "id": 760,
                "name": "Victoria Stadium",
                "address": "Winston Churchill Avenue",
                "city": "Gibraltar",
                "capacity": 5000,
                "surface": "artificial turf",
                "image": "https://media.api-sports.io/football/venues/760.png"
            }
        },
        {
            "team": {
                "id": 673,
                "name": "Sutjeska",
                "code": "SUT",
                "country": "Montenegro",
                "founded": 1927,
                "national": false,
                "logo": "https://media.api-sports.io/football/teams/673.png"
            },
            "venue": {
                "id": 1098,
                "name": "Stadion Kraj Bistrice",
                "address": "ul. Dragovi\u0107a Luka bb",
                "city": "Nik\u0161i\u0107",
                "capacity": 6180,
                "surface": "grass",
                "image": "https://media.api-sports.io/football/venues/1098.png"
            }
        },
        {
            "team": {
                "id": 707,
                "name": "FK Ventspils",
                "code": "VEN",
                "country": "Latvia",
                "founded": 1997,
                "national": false,
                "logo": "https://media.api-sports.io/football/teams/707.png"
            },
            "venue": {
                "id": 11511,
                "name": "Olimpisk\u0101 centra Ventspils Stadion\u0101",
                "address": "Sporta iel\u0101 7/9",
                "city": "Ventspils",
                "capacity": 3200,
                "surface": "grass",
                "image": "https://media.api-sports.io/football/venues/11511.png"
            }
        },
        {
            "team": {
                "id": 733,
                "name": "Standard Liege",
                "code": "STA",
                "country": "Belgium",
                "founded": 1898,
                "national": false,
                "logo": "https://media.api-sports.io/football/teams/733.png"
            },
            "venue": {
                "id": 192,
                "name": "Stade Maurice Dufrasne",
                "address": "Rue de la Centrale 2, Sclessin",
                "city": "Luik",
                "capacity": 27670,
                "surface": "grass",
                "image": "https://media.api-sports.io/football/venues/192.png"
            }
        },
        {
            "team": {
                "id": 1013,
                "name": "Grasshoppers",
                "code": "GRA",
                "country": "Switzerland",
                "founded": 1886,
                "national": false,
                "logo": "https://media.api-sports.io/football/teams/1013.png"
            },
            "venue": {
                "id": 1533,
                "name": "Stadion Letzigrund",
                "address": "Badenerstrasse 500",
                "city": "Z\u00fcrich",
                "capacity": 26104,
                "surface": "grass",
                "image": "https://media.api-sports.io/football/venues/1533.png"
            }
        },
        {
            "team": {
                "id": 2247,
                "name": "Apoel Nicosia",
                "code": "APO",
                "country": "Cyprus",
                "founded": 1926,
                "national": false,
                "logo": "https://media.api-sports.io/football/teams/2247.png"
            },
            "venue": {
                "id": 432,
                "name": "Neo GSP",
                "address": "Pangkiprion Avenue, Strovolos",
                "city": "Levkos\u00eda",
                "capacity": 22859,
                "surface": "grass",
                "image": "https://media.api-sports.io/football/venues/432.png"
            }
        },
        {
            "team": {
                "id": 2249,
                "name": "La Fiorita",
                "code": "FIO",
                "country": "San-Marino",
                "founded": 1967,
                "national": false,
                "logo": "https://media.api-sports.io/football/teams/2249.png"
            },
            "venue": {
                "id": 20185,
                "name": "Stadio Igor Crescentini",
                "address": "Strada Lodola",
                "city": "Montegiardino",
                "capacity": 500,
                "surface": "grass",
                "image": "https://media.api-sports.io/football/venues/20185.png"
            }
        },
        {
            "team": {
                "id": 2262,
                "name": "Dinamo Tbilisi",
                "code": "DIN",
                "country": "Georgia",
                "founded": 1925,
                "national": false,
                "logo": "https://media.api-sports.io/football/teams/2262.png"
            },
            "venue": {
                "id": 691,
                "name": "Boris Paichadze Dinamo Arena",
                "address": "2, Akaki Tsereteli Ave.",
                "city": "Tbilisi",
                "capacity": 54202,
                "surface": "grass",
                "image": "https://media.api-sports.io/football/venues/691.png"
            }
        },
        {
            "team": {
                "id": 2266,
                "name": "Cliftonville FC",
                "code": "CLI",
                "country": "Northern-Ireland",
                "founded": 1879,
                "national": false,
                "logo": "https://media.api-sports.io/football/teams/2266.png"
            },
            "venue": {
                "id": 1169,
                "name": "Solitude",
                "address": "Cliftonville Street",
                "city": "Belfast",
                "capacity": 5442,
                "surface": "artificial turf",
                "image": "https://media.api-sports.io/football/venues/1169.png"
            }
        },
        {
            "team": {
                "id": 2273,
                "name": "FC Levadia Tallinn",
                "code": "LEV",
                "country": "Estonia",
                "founded": 1998,
                "national": false,
                "logo": "https://media.api-sports.io/football/teams/2273.png"
            },
            "venue": {
                "id": 605,
                "name": "A. Le Coq Arena",
                "address": "Asula 4c",
                "city": "Tallinn",
                "capacity": 14405,
                "surface": "grass",
                "image": "https://media.api-sports.io/football/venues/605.png"
            }
        },
        {
            "team": {
                "id": 2276,
                "name": "FC Urartu",
                "code": "BAN",
                "country": "Armenia",
                "founded": 1992,
                "national": false,
                "logo": "https://media.api-sports.io/football/teams/2276.png"
            },
            "venue": {
                "id": 119,
                "name": "Urartu Stadium",
                "address": "ul. Al. Manukian, Malatia-Sebastia",
                "city": "Yerevan",
                "capacity": 5000,
                "surface": "grass",
                "image": "https://media.api-sports.io/football/venues/119.png"
            }
        },
        {
            "team": {
                "id": 2392,
                "name": "Debreceni VSC",
                "code": "DEB",
                "country": "Hungary",
                "founded": 1902,
                "national": false,
                "logo": "https://media.api-sports.io/football/teams/2392.png"
            },
            "venue": {
                "id": 795,
                "name": "Nagyerdei Stadion",
                "address": "Nagyerdei park 12",
                "city": "Debrecen",
                "capacity": 20340,
                "surface": "grass",
                "image": "https://media.api-sports.io/football/venues/795.png"
            }
        },
        {
            "team": {
                "id": 3396,
                "name": "AEL",
                "code": "LIM",
                "country": "Cyprus",
                "founded": 1930,
                "national": false,
                "logo": "https://media.api-sports.io/football/teams/3396.png"
            },
            "venue": {
                "id": 19616,
                "name": "Alphamega Stadium",
                "address": "93 Glastonos, Kapsalos",
                "city": "Kolossi",
                "capacity": 10700,
                "surface": "grass",
                "image": "https://media.api-sports.io/football/venues/19616.png"
            }
        },
        {
            "team": {
                "id": 3843,
                "name": "St Patrick's Athl.",
                "code": "PAT",
                "country": "Ireland",
                "founded": 1929,
                "national": false,
                "logo": "https://media.api-sports.io/football/teams/3843.png"
            },
            "venue": {
                "id": 2628,
                "name": "Richmond Park",
                "address": "125 Emmet Road, Inchicore",
                "city": "Dublin",
                "capacity": 5340,
                "surface": "grass",
                "image": "https://media.api-sports.io/football/venues/2628.png"
            }
        },
        {
            "team": {
                "id": 4133,
                "name": "HB",
                "code": null,
                "country": "Faroe-Islands",
                "founded": 1904,
                "national": false,
                "logo": "https://media.api-sports.io/football/teams/4133.png"
            },
            "venue": {
                "id": 609,
                "name": "Gundadalur",
                "address": "Gundadalsvegur",
                "city": "T\u00f3rshavn, Streymoy",
                "capacity": 5000,
                "surface": "artificial turf",
                "image": "https://media.api-sports.io/football/venues/609.png"
            }
        },
        {
            "team": {
                "id": 4563,
                "name": "Aktobe",
                "code": "AKT",
                "country": "Kazakhstan",
                "founded": 1967,
                "national": false,
                "logo": "https://media.api-sports.io/football/teams/4563.png"
            },
            "venue": {
                "id": 3450,
                "name": "Ortal\u0131q Stadion",
                "address": "prospekt Abulkhair Khan / ul. Mares&apos;yeva 2",
                "city": "Aktobe",
                "capacity": 13661,
                "surface": "grass",
                "image": "https://media.api-sports.io/football/venues/3450.png"
            }
        },
        {
            "team": {
                "id": 9151,
                "name": "Dnipro Dnipropetrovsk",
                "code": "DNE",
                "country": "Ukraine",
                "founded": 1918,
                "national": false,
                "logo": "https://media.api-sports.io/football/teams/9151.png"
            },
            "venue": {
                "id": 2426,
                "name": "Dnipro Arena",
                "address": "vul. Khersonska 7",
                "city": "Dnipropetrovs&apos;k",
                "capacity": 31003,
                "surface": "grass",
                "image": "https://media.api-sports.io/football/venues/2426.png"
            }
        }
    ]
}